custom_tool/GOT-OCR2.py
custom_tool/Moderation.py
custom_tool/RSS.py
custom_tool/SQL.py
custom_tool/WeChat_Official.py
custom_tool/__init__.py
custom_tool/amap.py
custom_tool/amap_decode.py
custom_tool/amap_encode.py
custom_tool/arxiv.py
custom_tool/browser.py
custom_tool/custom_format.py
custom_tool/dall_e.py
custom_tool/discord_bot.py
custom_tool/discord_monitor.py
custom_tool/easyocr_function.py
custom_tool/ebd_tool.py
custom_tool/example_tool.py
custom_tool/extra_parameters.py
custom_tool/feishu_download.py
custom_tool/feishu_download_img.py
custom_tool/feishu_get_history_msg.py
custom_tool/feishu_send_msg.py
custom_tool/file_control_safe.py
custom_tool/file_exist.py
custom_tool/file_online_delete.py
custom_tool/file_online_storage.py
custom_tool/fish_audio.py
custom_tool/folder_clear.py
custom_tool/gpt_sovits.py
custom_tool/html2img.py
custom_tool/ic_lora.py
custom_tool/image_hosting.py
custom_tool/img_lora.py
custom_tool/imges2imge.py
custom_tool/interrupt.py
custom_tool/json_extractor.py
custom_tool/json_parser.py
custom_tool/llavaloader.py
custom_tool/llm_lora.py
custom_tool/load_SQL.py
custom_tool/load_memo.py
custom_tool/load_redis.py
custom_tool/mcp_cli.py
custom_tool/md2excel.py
custom_tool/md2html.py
custom_tool/mermaid2img.py
custom_tool/miniparty.py
custom_tool/movie_editor.py
custom_tool/omost_json2py.py
custom_tool/open_web.py
custom_tool/openai_ebd.py
custom_tool/red_book_text_persona.py
custom_tool/save_persona.py
custom_tool/searxng.py
custom_tool/sleep.py
custom_tool/speed_change.py
custom_tool/srt2txt.py
custom_tool/stt.py
custom_tool/svg2img.py
custom_tool/switcher.py
custom_tool/text2json.py
custom_tool/url2image.py
custom_tool/whisper_party.py
janus/__init__.py
janus/models/__init__.py
janus/models/clip_encoder.py
janus/models/image_processing_vlm.py
janus/models/modeling_vlm.py
janus/models/processing_vlm.py
janus/models/projector.py
janus/models/siglip_vit.py
janus/models/vq_model.py
janus/utils/__init__.py
janus/utils/conversation.py
mseep_comfyui_llm_party-1.4.1.dist-info/licenses/LICENSE
mseep_comfyui_llm_party-1.4.1.dist-info/METADATA
mseep_comfyui_llm_party-1.4.1.dist-info/WHEEL
mseep_comfyui_llm_party-1.4.1.dist-info/top_level.txt
mseep_comfyui_llm_party-1.4.1.dist-info/RECORD
