Metadata-Version: 2.4
Name: mseep-comfyui_llm_party
Version: 1.4.1
Summary: A set of block-based LLM agent node libraries designed for ComfyUI.This project aims to develop a complete set of nodes for LLM workflow construction based on comfyui. It allows users to quickly and conveniently build their own LLM workflows and easily integrate them into their existing SD workflows.
Home-page: 
Author: mseep
Author-email: support@skydeck.ai
Maintainer: mseep
Maintainer-email: support@skydeck.ai
Keywords: mseep
Classifier: Programming Language :: Python :: 3
Classifier: License :: OSI Approved :: MIT License
Classifier: Operating System :: OS Independent
Requires-Python: >=3.6
License-File: LICENSE
Requires-Dist: beautifulsoup4
Requires-Dist: docx2txt
Requires-Dist: langchain
Requires-Dist: langchain-community
Requires-Dist: langchain-text-splitters
Requires-Dist: openai>=1.57.4
Requires-Dist: openpyxl
Requires-Dist: pandas
Requires-Dist: pytz
Requires-Dist: requests
Requires-Dist: xlrd
Requires-Dist: faiss-cpu
Requires-Dist: websocket-client
Requires-Dist: streamlit
Requires-Dist: virtualenv
Requires-Dist: tiktoken
Requires-Dist: transformers
Requires-Dist: transformers-stream-generator
Requires-Dist: optimum
Requires-Dist: pdfplumber
Requires-Dist: wikipedia
Requires-Dist: arxiv
Requires-Dist: bitsandbytes
Requires-Dist: accelerate
Requires-Dist: fastapi
Requires-Dist: py-cpuinfo
Requires-Dist: diskcache
Requires-Dist: requests-toolbelt
Requires-Dist: tabulate
Requires-Dist: charset-normalizer
Requires-Dist: tenacity
Requires-Dist: cpm-kernels
Requires-Dist: pydub
Requires-Dist: keyboard
Requires-Dist: sounddevice
Requires-Dist: neo4j
Requires-Dist: soundfile
Requires-Dist: langchain-openai
Requires-Dist: sentence-transformers
Requires-Dist: uvicorn
Requires-Dist: google-generativeai
Requires-Dist: llama-index
Requires-Dist: html2image
Requires-Dist: markdown
Requires-Dist: selenium
Requires-Dist: librosa
Requires-Dist: ffmpeg-python
Requires-Dist: moviepy
Requires-Dist: html5lib
Requires-Dist: easyocr
Requires-Dist: feedparser
Requires-Dist: psutil
Requires-Dist: verovio
Requires-Dist: mdtex2html
Requires-Dist: markdownify
Requires-Dist: srt
Requires-Dist: peft
Requires-Dist: scipy>=1.15.2
Requires-Dist: json-repair>=0.44.0
Requires-Dist: redis>=5.3.0
Requires-Dist: aisuite[all]>=0.1.11
Requires-Dist: fish-audio-sdk>=2025.4.2
Requires-Dist: httpx<=0.27.2
Requires-Dist: mcp>=1.6.0
Requires-Dist: qwen-vl-utils[decord]>=0.0.11
Requires-Dist: attrdict>=2.0.1
Requires-Dist: docstring-parser>=0.16
Requires-Dist: langchain-ollama>=0.3.2
Requires-Dist: timm>=1.0.15
Dynamic: author
Dynamic: author-email
Dynamic: classifier
Dynamic: description
Dynamic: description-content-type
Dynamic: keywords
Dynamic: license-file
Dynamic: maintainer
Dynamic: maintainer-email
Dynamic: requires-dist
Dynamic: requires-python
Dynamic: summary
